postgresql/__init__.py
postgresql/postgresql.py
insidepostgresql-0.0.3.dist-info/LICENSE
insidepostgresql-0.0.3.dist-info/METADATA
insidepostgresql-0.0.3.dist-info/WHEEL
insidepostgresql-0.0.3.dist-info/top_level.txt
insidepostgresql-0.0.3.dist-info/RECORD
