Metadata-Version: 2.1
Name: insidepostgresql
Version: 0.0.3
Summary: Check and analyze a PostgreSQL cluster.
Home-page: https://github.com/adiosamig/insidepgs
Author: Huseyin Demir
Author-email: huseyin.d3r@gmail.com
Project-URL: Bug Tracker, https://github.com/adiosamig/insidepgs/issues
Classifier: Programming Language :: Python :: 3
Classifier: License :: OSI Approved :: MIT License
Classifier: Operating System :: OS Independent
Requires-Python: >=3.6
License-File: LICENSE
Requires-Dist: psycopg2-binary
Requires-Dist: tabulate
Requires-Dist: datetime
